takuhai/__init__.py
takuhai/main.py
takuhai/serve.py
takuhai-1.0.0.dist-info/LICENSE
takuhai-1.0.0.dist-info/METADATA
takuhai-1.0.0.dist-info/WHEEL
takuhai-1.0.0.dist-info/entry_points.txt
takuhai-1.0.0.dist-info/top_level.txt
takuhai-1.0.0.dist-info/RECORD
