Metadata-Version: 2.1
Name: takuhai
Version: 1.0.0
Summary: A Pelican server
Home-page: https://github.com/daizutabi/takuhai
Author: daizutabi
Author-email: daizutabi@gmail.com
License: MIT
Platform: UNKNOWN
Classifier: Development Status :: 3 - Alpha
Classifier: License :: OSI Approved :: MIT License
Classifier: Operating System :: OS Independent
Classifier: Programming Language :: Python
Classifier: Programming Language :: Python :: 3
Classifier: Programming Language :: Python :: 3.6
Classifier: Programming Language :: Python :: 3.7
Classifier: Topic :: Documentation
Requires-Dist: pelican
Requires-Dist: livereload
Requires-Dist: click
